{"namedChunkGroups":{"polyfill":{"name":"polyfill","assets":[{"name":"webpack-runtime-99d71ab667f4cabab3ce.js","size":5419},{"name":"polyfill-9297e683e8587f367349.js","size":85308}],"filteredAssets":0,"assetsSize":90727,"filteredAuxiliaryAssets":2,"auxiliaryAssetsSize":228574},"app":{"name":"app","assets":[{"name":"webpack-runtime-99d71ab667f4cabab3ce.js","size":5419},{"name":"styles.c1531b9106885797674f.css","size":169021},{"name":"framework-e886f61ee3e03a6355e5.js","size":129941},{"name":"app-4a7b28c48e58d6a7ef26.js","size":68757}],"filteredAssets":0,"assetsSize":373138,"filteredAuxiliaryAssets":3,"auxiliaryAssetsSize":659990},"component---src-pages-404-js":{"name":"component---src-pages-404-js","assets":[{"name":"styles.c1531b9106885797674f.css","size":169021},{"name":"commons-c47b22fc4fa2402e9dca.js","size":25840},{"name":"fa6404d652d08cc3132e15f16a52924a7eded953-f0e4d4f814837df5d81e.js","size":16314},{"name":"component---src-pages-404-js-8fe377ffbead3a6b5899.js","size":485}],"filteredAssets":0,"assetsSize":211660,"filteredAuxiliaryAssets":3,"auxiliaryAssetsSize":176401},"component---src-pages-index-js":{"name":"component---src-pages-index-js","assets":[{"name":"styles.c1531b9106885797674f.css","size":169021},{"name":"commons-c47b22fc4fa2402e9dca.js","size":25840},{"name":"component---src-pages-index-js-3d082b8a9d77620cbd66.js","size":3033}],"filteredAssets":0,"assetsSize":197894,"filteredAuxiliaryAssets":2,"auxiliaryAssetsSize":111610},"component---src-pages-p-cookburn-js":{"name":"component---src-pages-p-cookburn-js","assets":[{"name":"styles.c1531b9106885797674f.css","size":169021},{"name":"commons-c47b22fc4fa2402e9dca.js","size":25840},{"name":"component---src-pages-p-cookburn-js-bdec1fad1698ff36a847.js","size":22372}],"filteredAssets":0,"assetsSize":217233,"filteredAuxiliaryAssets":18,"auxiliaryAssetsSize":3128349},"component---src-pages-p-ds-js":{"name":"component---src-pages-p-ds-js","assets":[{"name":"styles.c1531b9106885797674f.css","size":169021},{"name":"commons-c47b22fc4fa2402e9dca.js","size":25840},{"name":"component---src-pages-p-ds-js-ac752b598b605d5213d3.js","size":3033}],"filteredAssets":0,"assetsSize":197894,"filteredAuxiliaryAssets":3,"auxiliaryAssetsSize":200491},"component---src-pages-p-dw-js":{"name":"component---src-pages-p-dw-js","assets":[{"name":"styles.c1531b9106885797674f.css","size":169021},{"name":"commons-c47b22fc4fa2402e9dca.js","size":25840},{"name":"component---src-pages-p-dw-js-7f5e0d9fcaba14078f78.js","size":4032}],"filteredAssets":0,"assetsSize":198893,"filteredAuxiliaryAssets":3,"auxiliaryAssetsSize":203967},"component---src-pages-projects-js":{"name":"component---src-pages-projects-js","assets":[{"name":"styles.c1531b9106885797674f.css","size":169021},{"name":"commons-c47b22fc4fa2402e9dca.js","size":25840},{"name":"component---src-pages-projects-js-2245ee2643845131f0be.js","size":9269}],"filteredAssets":0,"assetsSize":204130,"filteredAuxiliaryAssets":11,"auxiliaryAssetsSize":1452578},"component---src-pages-using-typescript-tsx":{"name":"component---src-pages-using-typescript-tsx","assets":[{"name":"styles.c1531b9106885797674f.css","size":169021},{"name":"commons-c47b22fc4fa2402e9dca.js","size":25840},{"name":"fa6404d652d08cc3132e15f16a52924a7eded953-f0e4d4f814837df5d81e.js","size":16314},{"name":"component---src-pages-using-typescript-tsx-4ea487bc3fe1743a8355.js","size":1332}],"filteredAssets":0,"assetsSize":212507,"filteredAuxiliaryAssets":3,"auxiliaryAssetsSize":177820}},"assetsByChunkName":{"polyfill":["webpack-runtime-99d71ab667f4cabab3ce.js","polyfill-9297e683e8587f367349.js"],"app":["webpack-runtime-99d71ab667f4cabab3ce.js","styles.c1531b9106885797674f.css","framework-e886f61ee3e03a6355e5.js","app-4a7b28c48e58d6a7ef26.js"],"component---src-pages-404-js":["styles.c1531b9106885797674f.css","commons-c47b22fc4fa2402e9dca.js","fa6404d652d08cc3132e15f16a52924a7eded953-f0e4d4f814837df5d81e.js","component---src-pages-404-js-8fe377ffbead3a6b5899.js"],"component---src-pages-index-js":["styles.c1531b9106885797674f.css","commons-c47b22fc4fa2402e9dca.js","component---src-pages-index-js-3d082b8a9d77620cbd66.js"],"component---src-pages-p-cookburn-js":["styles.c1531b9106885797674f.css","commons-c47b22fc4fa2402e9dca.js","component---src-pages-p-cookburn-js-bdec1fad1698ff36a847.js"],"component---src-pages-p-ds-js":["styles.c1531b9106885797674f.css","commons-c47b22fc4fa2402e9dca.js","component---src-pages-p-ds-js-ac752b598b605d5213d3.js"],"component---src-pages-p-dw-js":["styles.c1531b9106885797674f.css","commons-c47b22fc4fa2402e9dca.js","component---src-pages-p-dw-js-7f5e0d9fcaba14078f78.js"],"component---src-pages-projects-js":["styles.c1531b9106885797674f.css","commons-c47b22fc4fa2402e9dca.js","component---src-pages-projects-js-2245ee2643845131f0be.js"],"component---src-pages-using-typescript-tsx":["styles.c1531b9106885797674f.css","commons-c47b22fc4fa2402e9dca.js","fa6404d652d08cc3132e15f16a52924a7eded953-f0e4d4f814837df5d81e.js","component---src-pages-using-typescript-tsx-4ea487bc3fe1743a8355.js"]},"childAssetsByChunkName":{}}